rlstatsdb/__init__.py
rlstatsdb/_manager.py
rlstatsdb/constants.py
rlstatsdb/models.py
rlstatsdb/types.py
rlstatsdb/utils.py
rlstatsdb-0.0.4.dist-info/LICENSE
rlstatsdb-0.0.4.dist-info/METADATA
rlstatsdb-0.0.4.dist-info/WHEEL
rlstatsdb-0.0.4.dist-info/top_level.txt
rlstatsdb-0.0.4.dist-info/RECORD
