Metadata-Version: 2.1
Name: rlstatsdb
Version: 0.0.4
Summary: A simple and pythonic system to store, retrieve, and analyze Rocket League replay stats as returned from ballchasing.com's API
Author-email: "Tanner B. Corcoran" <tannerbcorcoran@gmail.com>
Project-URL: Homepage, https://github.com/tanrbobanr/rlstatsdb
Classifier: Programming Language :: Python :: 3
Classifier: License :: OSI Approved :: MIT License
Classifier: Operating System :: OS Independent
Requires-Python: >=3.11
License-File: LICENSE
Requires-Dist: prepr (>=0.0.6)
